pyasgard/__init__.py
pyasgard/asgardcommand.py
pyasgard/endpoints.py
pyasgard/exceptions.py
pyasgard/htmltodict.py
pyasgard/pyasgard.py
pyasgard/version.py
pyasgard-1.5.dist-info/DESCRIPTION.rst
pyasgard-1.5.dist-info/METADATA
pyasgard-1.5.dist-info/RECORD
pyasgard-1.5.dist-info/WHEEL
pyasgard-1.5.dist-info/metadata.json
pyasgard-1.5.dist-info/top_level.txt
