Metadata-Version: 2.0
Name: pyasgard
Version: 1.5
Summary: Python library for working with the Asgard api.
Home-page: https://github.com/gogoair/pyasgard
Author: Sijis Aviles
Author-email: saviles@gogoair.com
License: MIT
Download-URL: https://github.com/gogoair/pyasgard
Keywords: asgard api python netflixoss
Platform: OS Independent
Classifier: Development Status :: 5 - Production/Stable
Classifier: Intended Audience :: Developers
Classifier: Programming Language :: Python :: 2.7
Classifier: Programming Language :: Python :: 3.4
Classifier: Programming Language :: Python :: 3.5
Classifier: License :: OSI Approved :: MIT License
Classifier: Operating System :: OS Independent
Requires-Dist: beautifulsoup4
Requires-Dist: requests
